pytest_broadcaster/__about__.py
pytest_broadcaster/__about__.pyi
pytest_broadcaster/__init__.py
pytest_broadcaster/plugin.py
pytest_broadcaster/py.typed
pytest_broadcaster/_internal/__init__.py
pytest_broadcaster/_internal/_fields.py
pytest_broadcaster/_internal/_json_files.py
pytest_broadcaster/_internal/_pyproject.py
pytest_broadcaster/_internal/_reporter.py
pytest_broadcaster/_internal/_utils.py
pytest_broadcaster/_internal/_webhook.py
pytest_broadcaster/hooks/__init__.py
pytest_broadcaster/interfaces/__init__.py
pytest_broadcaster/models/__init__.py
pytest_broadcaster/models/collect_report.py
pytest_broadcaster/models/error_message.py
pytest_broadcaster/models/location.py
pytest_broadcaster/models/outcome.py
pytest_broadcaster/models/project.py
pytest_broadcaster/models/python_distribution.py
pytest_broadcaster/models/session_end.py
pytest_broadcaster/models/session_event.py
pytest_broadcaster/models/session_result.py
pytest_broadcaster/models/session_start.py
pytest_broadcaster/models/test_case.py
pytest_broadcaster/models/test_case_call.py
pytest_broadcaster/models/test_case_end.py
pytest_broadcaster/models/test_case_error.py
pytest_broadcaster/models/test_case_report.py
pytest_broadcaster/models/test_case_setup.py
pytest_broadcaster/models/test_case_teardown.py
pytest_broadcaster/models/test_directory.py
pytest_broadcaster/models/test_module.py
pytest_broadcaster/models/test_suite.py
pytest_broadcaster/models/traceback.py
pytest_broadcaster/models/warning_message.py
pytest_broadcaster-0.11.0.dist-info/METADATA
pytest_broadcaster-0.11.0.dist-info/WHEEL
pytest_broadcaster-0.11.0.dist-info/entry_points.txt
pytest_broadcaster-0.11.0.dist-info/licenses/LICENSE
pytest_broadcaster-0.11.0.dist-info/RECORD
