Metadata-Version: 2.4
Name: pytest-broadcaster
Version: 0.11.0
Summary: Pytest plugin to broadcast pytest output to various destinations
Project-URL: Source, https://github.com/charbonnierg/pytest-broadcaster
Project-URL: Tracker, https://github.com/charbonnierg/pytest-broadcaster/issues
Author-email: Guillaume Charbonnier <gu.charbon@gmail.com>
License-File: LICENSE
Classifier: Development Status :: 3 - Alpha
Classifier: Framework :: Pytest
Classifier: Intended Audience :: Developers
Classifier: License :: OSI Approved :: MIT License
Classifier: Operating System :: OS Independent
Classifier: Programming Language :: Python :: 3
Classifier: Programming Language :: Python :: 3.9
Classifier: Programming Language :: Python :: 3.10
Classifier: Programming Language :: Python :: 3.11
Classifier: Programming Language :: Python :: 3.12
Classifier: Programming Language :: Python :: 3.13
Classifier: Topic :: Software Development :: Testing
Requires-Python: >=3.9
Requires-Dist: pytest
Requires-Dist: tomli>=1; python_version < '3.11'
